SoEasyData/GetMLData.py
SoEasyData/GetRData.py
SoEasyData/GetSeabornData.py
SoEasyData/GetStataData.py
SoEasyData/GetStatsmodelData.py
SoEasyData/__init__.py
soeasydata-0.0.2.dist-info/METADATA
soeasydata-0.0.2.dist-info/WHEEL
soeasydata-0.0.2.dist-info/licenses/LICENSE
soeasydata-0.0.2.dist-info/RECORD
