Metadata-Version: 2.1
Name: SoEasyData
Version: 0.0.2
Summary: 快速获取数据的简洁程序库
Project-URL: Homepage, https://github.com/LiuAndy-art/SoEasyData
Project-URL: Documentation, https://github.com/LiuAndy-art/SoEasyData
Project-URL: Repository, https://github.com/LiuAndy-art/SoEasyData
Author-email: LiuAndy <andylau_dh@163.com>
Maintainer-email: LiuAndy <andylau_dh@163.com>
License: MIT License
License-File: LICENSE
Keywords: 函数封装,数据获取,简介代码
Classifier: License :: OSI Approved :: MIT License
Classifier: Operating System :: OS Independent
Classifier: Programming Language :: Python :: 3
Requires-Python: >=3.8
Requires-Dist: matplotlib
Requires-Dist: numpy
Requires-Dist: openml
Requires-Dist: openpyxl
Requires-Dist: pandas
Requires-Dist: pyreadstat
Requires-Dist: seaborn
Requires-Dist: statsmodels
Requires-Dist: xlrd
Requires-Dist: xlsxwriter
Requires-Dist: xlwt
